{
  "db": "PostgreSQL",
  "1e49128cf7937beb77dc23de679ac9fd1e37cea717614d6a704f5142f14c46ad": {
    "query": "\n    INSERT INTO users (id, username, email, password)\n    VALUES ($1, $2, $3, $4)\n    ",
    "describe": {
      "columns": [],
      "parameters": {
        "Left": [
          "Uuid",
          "Text",
          "Text",
          "Text"
        ]
      },
      "nullable": []
    }
  },
  "90b76bc6f4e1d6193410f08a1383cd545cc4e59948a4f9be5e8173d50d1fefae": {
    "query": "\n        SELECT id, email, password\n        FROM users\n        WHERE email = $1\n        ",
    "describe": {
      "columns": [
        {
          "ordinal": 0,
          "name": "id",
          "type_info": "Uuid"
        },
        {
          "ordinal": 1,
          "name": "email",
          "type_info": "Text"
        },
        {
          "ordinal": 2,
          "name": "password",
          "type_info": "Text"
        }
      ],
      "parameters": {
        "Left": [
          "Text"
        ]
      },
      "nullable": [
        false,
        false,
        false
      ]
    }
  },
  "a1fea900c45238b9e31fa71f1948ef7b37c172de78e2b793723a904b5043cabb": {
    "query": "\n        INSERT INTO servers (id, name, owner_id)\n        VALUES ($1, $2, $3)\n        ",
    "describe": {
      "columns": [],
      "parameters": {
        "Left": [
          "Uuid",
          "Text",
          "Uuid"
        ]
      },
      "nullable": []
    }
  },
  "bfad0f1033b76edc2d37b1f33d9f36dc38065e08b70a2877fd980400c50bd1e1": {
    "query": "\n        SELECT id, username, email, updated_at, created_at\n        FROM users\n        WHERE id = $1\n        ",
    "describe": {
      "columns": [
        {
          "ordinal": 0,
          "name": "id",
          "type_info": "Uuid"
        },
        {
          "ordinal": 1,
          "name": "username",
          "type_info": "Text"
        },
        {
          "ordinal": 2,
          "name": "email",
          "type_info": "Text"
        },
        {
          "ordinal": 3,
          "name": "updated_at",
          "type_info": "Timestamptz"
        },
        {
          "ordinal": 4,
          "name": "created_at",
          "type_info": "Timestamptz"
        }
      ],
      "parameters": {
        "Left": [
          "Uuid"
        ]
      },
      "nullable": [
        false,
        false,
        false,
        false,
        false
      ]
    }
  },
  "c7e4a5d6ab6847d62422066f5c8c66e60ab4af814c16e927ed7720b7a0808ab8": {
    "query": "\n        INSERT INTO users_servers (id, user_id, server_id)\n        VALUES ($1, $2, $3)\n        ",
    "describe": {
      "columns": [],
      "parameters": {
        "Left": [
          "Uuid",
          "Uuid",
          "Uuid"
        ]
      },
      "nullable": []
    }
  },
  "faa000e9c341eed90687fe4dacf5cd8dfa0c96e34ccfb6619c056be1df553236": {
    "query": "\n        SELECT servers.*\n        FROM users_servers\n        INNER JOIN servers ON users_servers.server_id = servers.id\n        WHERE users_servers.user_id = $1\n        ",
    "describe": {
      "columns": [
        {
          "ordinal": 0,
          "name": "id",
          "type_info": "Uuid"
        },
        {
          "ordinal": 1,
          "name": "name",
          "type_info": "Text"
        },
        {
          "ordinal": 2,
          "name": "owner_id",
          "type_info": "Uuid"
        },
        {
          "ordinal": 3,
          "name": "updated_at",
          "type_info": "Timestamptz"
        },
        {
          "ordinal": 4,
          "name": "created_at",
          "type_info": "Timestamptz"
        }
      ],
      "parameters": {
        "Left": [
          "Uuid"
        ]
      },
      "nullable": [
        false,
        false,
        false,
        false,
        false
      ]
    }
  }
}